INSTALL.rst
LICENSE
MANIFEST.in
README.rst
requirements.txt
setup.cfg
setup.py
tasks.py
src/pushtogether_math/__init__.py
src/pushtogether_math/cluster.py
src/pushtogether_math/data_converter.py
src/pushtogether_math/decomposer.py
src/pushtogether_math/kmeans.py
src/pushtogether_math.egg-info/PKG-INFO
src/pushtogether_math.egg-info/SOURCES.txt
src/pushtogether_math.egg-info/dependency_links.txt
src/pushtogether_math.egg-info/not-zip-safe
src/pushtogether_math.egg-info/requires.txt
src/pushtogether_math.egg-info/top_level.txt