Metadata-Version: 1.1
Name: pushtogether-math
Version: 0.1.20
Summary: The Pushing Together Kmeans clustering tool
Home-page: https://gitlab.com/empurrandojuntos/pushtogether-math
Author: Luan Guimarães Lacerda
Author-email: luang@protonmail.ch
License: GNU General Public License (GPL)
Keywords: machinelearning,pushingtogether,pushtogether,kmeans,clustering,math
Platform: UNKNOWN
Classifier: Development Status :: 3 - Alpha
Classifier: Intended Audience :: Developers
Classifier: Operating System :: POSIX
Classifier: Programming Language :: Python
Classifier: Programming Language :: Python :: 3.6
Classifier: Topic :: Software Development :: Libraries
